coverage_control/_core.cpython-312-x86_64-linux-gnu.so
coverage_control/__init__.py
coverage_control/io_utils.py
coverage_control/_version.py
coverage_control/_version.pyi
coverage_control/coverage_env_utils.py
coverage_control/py.typed
coverage_control/include/CoverageControl/world_idf.h
coverage_control/include/CoverageControl/typedefs.h
coverage_control/include/CoverageControl/robot_model.h
coverage_control/include/CoverageControl/constants.h
coverage_control/include/CoverageControl/plotter.h
coverage_control/include/CoverageControl/Config.h
coverage_control/include/CoverageControl/bivariate_normal_distribution.h
coverage_control/include/CoverageControl/parameters.h
coverage_control/include/CoverageControl/cuda_utils.h
coverage_control/include/CoverageControl/vec2d.h
coverage_control/include/CoverageControl/coverage_system.h
coverage_control/include/CoverageControl/geographiclib_wrapper.h
coverage_control/include/CoverageControl/voronoi.h
coverage_control/include/CoverageControl/generate_world_map.h
coverage_control/include/CoverageControl/map_utils.h
coverage_control/include/CoverageControl/extern/json/json.hpp
coverage_control/include/CoverageControl/extern/tomlplusplus/toml.hpp
coverage_control/include/CoverageControl/extern/cuda_helpers/helper_string.h
coverage_control/include/CoverageControl/extern/cuda_helpers/helper_cuda.h
coverage_control/include/CoverageControl/extern/gnuplot/gnuplot-iostream.h
coverage_control/include/CoverageControl/extern/lsap/LICENSE
coverage_control/include/CoverageControl/extern/lsap/README.txt
coverage_control/include/CoverageControl/extern/lsap/Hungarian.h
coverage_control/include/CoverageControl/cuda/geometry_utils.cuh
coverage_control/include/CoverageControl/algorithms/decentralized_cvt.h
coverage_control/include/CoverageControl/algorithms/oracle_explore_exploit.h
coverage_control/include/CoverageControl/algorithms/clairvoyant_cvt.h
coverage_control-1.3.1.dist-info/RECORD
coverage_control-1.3.1.dist-info/METADATA
coverage_control-1.3.1.dist-info/WHEEL
coverage_control-1.3.1.dist-info/licenses/LICENSE
