Metadata-Version: 2.1
Name: coverage_control
Version: 1.3.1
Summary: Library for large-scale coverage control using robot swarms
Author-Email: Saurav Agarwal <agr.saurav1@gmail.com>
License:                     GNU GENERAL PUBLIC LICENSE
Classifier: Development Status :: 4 - Beta
Classifier: Intended Audience :: Science/Research
Classifier: Intended Audience :: Education
Classifier: License :: OSI Approved :: GNU General Public License v3 (GPLv3)
Classifier: Operating System :: OS Independent
Classifier: Programming Language :: C++
Classifier: Programming Language :: Python :: 3
Classifier: Framework :: Robot Framework
Classifier: Topic :: Scientific/Engineering :: Artificial Intelligence
Classifier: Environment :: GPU :: NVIDIA CUDA
Project-URL: Homepage, https://github.com/KumarRobotics/CoverageControl
Project-URL: Bug tracker, https://github.com/KumarRobotics/CoverageControl/issues
Project-URL: Discussions, https://github.com/KumarRobotics/CoverageControl/discussions
Project-URL: Changelog, https://github.com/KumarRobotics/CoverageControl/releases
Requires-Python: >=3.10
Requires-Dist: numpy
Requires-Dist: pyyaml
Requires-Dist: toml; python_version < "3.11"
Requires-Dist: rich
Requires-Dist: torch>=2.5; extra == "nn"
Requires-Dist: torchvision>=0.20; extra == "nn"
Requires-Dist: torch_geometric>=2.6; extra == "nn"
Requires-Dist: pytest>=6; extra == "core-test"
Requires-Dist: pytest>=6; extra == "test"
Requires-Dist: torch>=2.5; extra == "test"
Requires-Dist: torchvision; extra == "test"
Provides-Extra: nn
Provides-Extra: core-test
Provides-Extra: test
